<?xml version="1.0" encoding="UTF-8"?>
<!--
  ~ Copyright 2017-2019 EPAM Systems, Inc. (https://www.epam.com/)
  ~
  ~ Licensed under the Apache License, Version 2.0 (the "License");
  ~ you may not use this file except in compliance with the License.
  ~ You may obtain a copy of the License at
  ~
  ~     http://www.apache.org/licenses/LICENSE-2.0
  ~
  ~ Unless required by applicable law or agreed to in writing, software
  ~ distributed under the License is distributed on an "AS IS" BASIS,
  ~ WITHOUT WARRANTIES OR CONDITIONS OF ANY KIND, either express or implied.
  ~ See the License for the specific language governing permissions and
  ~ limitations under the License.
  -->

<beans xmlns="http://www.springframework.org/schema/beans"
       xmlns:xsi="http://www.w3.org/2001/XMLSchema-instance"
       xsi:schemaLocation="http://www.springframework.org/schema/beans http://www.springframework.org/schema/beans/spring-beans.xsd">
    <bean class="com.epam.pipeline.dao.filter.FilterDao" id="filterDao" autowire="byName">
        <property name="filterPipelineRunsBaseQuery">
            <value>
                <![CDATA[
                    SELECT
                        r.run_id,
                        r.pipeline_id,
                        r.version,
                        r.start_date,
                        r.end_date,
                        r.parameters,
                        r.status,
                        r.terminating,
                        r.pod_id,
                        r.node_type,
                        r.node_disk,
                        r.node_ip,
                        r.node_id,
                        r.node_name,
                        r.node_image,
                        r.node_cloud_region,
                        r.docker_image,
                        r.cmd_template,
                        r.actual_cmd,
                        r.timeout,
                        r.owner,
                        r.service_url,
                        r.pod_ip,
                        r.commit_status,
                        r.last_change_commit_time,
                        r.config_name,
                        r.node_count,
                        r.parent_id,
                        r.entities_ids,
                        r.is_spot,
                        r.configuration_id,
                        r.pod_status,
                        r.prolonged_at_time,
                        r.last_notification_time,
                        r.last_idle_notification_time,
                        r.exec_preferences,
                        r.pretty_url,
                        r.price_per_hour,
                        r.state_reason,
                        r.non_pause,
                        r.node_real_disk,
                        r.node_cloud_provider,
                        r.tags,
                        pipelines.pipeline_name
                    FROM
                        pipeline.pipeline_run r
                    LEFT JOIN pipeline.pipeline pipelines ON (pipelines.pipeline_id = r.pipeline_id)
                    WHERE @WHERE@
                    ORDER BY r.run_id DESC
                    LIMIT :LIMIT OFFSET :OFFSET
                ]]>
            </value>
        </property>
        <property name="countFilteredPipelineRunsBaseQuery">
            <value>
                <![CDATA[
                    SELECT
                        count(*) as count
                    FROM
                        pipeline.pipeline_run r
                    LEFT JOIN pipeline.pipeline pipelines ON (pipelines.pipeline_id = r.pipeline_id)
                    WHERE @WHERE@
                ]]>
            </value>
        </property>
    </bean>
</beans>
